LICENSE
README.rst
setup.py
database_files/__init__.py
database_files/manager.py
database_files/models.py
database_files/storage.py
database_files/urls.py
database_files/views.py
database_files/migrations/0001_initial.py
database_files/migrations/__init__.py
database_files/tests/__init__.py
database_files/tests/models.py
database_files/tests/settings.py
database_files/tests/tests.py
database_files/tests/files/lena.png
database_files/tests/files/lorem.txt
database_files/tests/files/other_files/ipsum.txt
database_files/tests/files/other_files/lena.png
database_files/tests/files/qq/qqqq.qqq
database_files/tests/fixtures/test_data.json
django_database_files_ny.egg-info/PKG-INFO
django_database_files_ny.egg-info/SOURCES.txt
django_database_files_ny.egg-info/dependency_links.txt
django_database_files_ny.egg-info/top_level.txt