Metadata-Version: 1.1
Name: django-database-files-ny
Version: 0.2.3
Summary: A storage system for Django that stores uploaded files in the database.
Home-page: http://github.com/legostormtroopr/django-database-files/
Author: Sam Spencer
Author-email: sam@aristotlemetadata.com
License: UNKNOWN
Platform: UNKNOWN
Classifier: Development Status :: 4 - Beta
Classifier: Framework :: Django
Classifier: Intended Audience :: Developers
Classifier: License :: OSI Approved :: BSD License
Classifier: Operating System :: OS Independent
Classifier: Programming Language :: Python
